mybad/__init__.py
mybad/__init__.pyc
mybad/errors.py
mybad/errors.pyc
mybad/tests/__init__.py
mybad/tests/__main__.py
mybad/tests/helper.py
mybad/tests/test_errors.py
mybad-0.2.0.dist-info/METADATA
mybad-0.2.0.dist-info/WHEEL
mybad-0.2.0.dist-info/top_level.txt
mybad-0.2.0.dist-info/zip-safe
mybad-0.2.0.dist-info/RECORD
