Metadata-Version: 2.1
Name: mybad
Version: 0.2.0
Summary: My friendly error base class - for Python.
Home-page: https://github.com/grimen/python-mybad
Author: Jonas Grimfelt
Author-email: grimen@gmail.com
License: MIT
Download-URL: https://github.com/grimen/python-mybad
Project-URL: bugs, https://github.com/grimen/python-mybad/issues
Project-URL: repository, https://github.com/grimen/python-mybad
Keywords: error,errors,baseclass,meta,debug,inspector,pretty,color,colors,detailed,stacktrace
Platform: UNKNOWN
Classifier: Topic :: Software Development :: Libraries
Classifier: Development Status :: 5 - Production/Stable
Classifier: Intended Audience :: Developers
Classifier: License :: OSI Approved :: MIT License
Classifier: Operating System :: POSIX
Classifier: Programming Language :: Python
Classifier: Programming Language :: Python :: 2
Classifier: Programming Language :: Python :: 3
Classifier: Programming Language :: Python :: Implementation :: CPython
Classifier: Programming Language :: Python :: Implementation :: PyPy
Requires-Dist: setupextras (>=0.1.5)
Requires-Dist: six (>=1.12.0)
Requires-Dist: rootpath (>=0.1.1)
Requires-Dist: inspecta (>=0.1.3)
Requires-Dist: attributedict (>=0.3.0)
Requires-Dist: termcolor (>=1.1.0)
Requires-Dist: colour-runner (>=0.0.5)
Requires-Dist: deepdiff (>=3.3.0)
Requires-Dist: tox (>=3.0.0)
Requires-Dist: coverage (>=4.5.2)
Requires-Dist: codecov (>=2.0.15)
